{
  "annotations": {
    "list": [
      {
        "builtIn": 1,
        "datasource": {
          "type": "grafana",
          "uid": "-- Grafana --"
        },
        "enable": true,
        "hide": true,
        "iconColor": "rgba(0, 211, 255, 1)",
        "name": "Annotations & Alerts",
        "type": "dashboard"
      }
    ]
  },
  "editable": true,
  "fiscalYearStartMonth": 0,
  "graphTooltip": 0,
  "id": 2,
  "links": [],
  "panels": [
    {
      "datasource": {
        "type": "prometheus",
        "uid": "PBFA97CFB590B2093"
      },
      "description": "Compared to the maximum value measured over the past 90 days.",
      "fieldConfig": {
        "defaults": {
          "color": {
            "mode": "thresholds"
          },
          "decimals": 1,
          "displayName": "${__field.labels.pool_name}",
          "mappings": [],
          "thresholds": {
            "mode": "percentage",
            "steps": [
              {
                "color": "green"
              },
              {
                "color": "yellow",
                "value": 20
              },
              {
                "color": "#EAB839",
                "value": 50
              },
              {
                "color": "red",
                "value": 80
              }
            ]
          },
          "unit": "percentunit"
        },
        "overrides": []
      },
      "gridPos": {
        "h": 6,
        "w": 24,
        "x": 0,
        "y": 0
      },
      "id": 8,
      "options": {
        "minVizHeight": 75,
        "minVizWidth": 75,
        "orientation": "auto",
        "reduceOptions": {
          "calcs": [
            "lastNotNull"
          ],
          "fields": "",
          "values": false
        },
        "showThresholdLabels": false,
        "showThresholdMarkers": true,
        "sizing": "auto"
      },
      "pluginVersion": "12.0.0",
      "targets": [
        {
          "datasource": {
            "type": "prometheus",
            "uid": "PBFA97CFB590B2093"
          },
          "disableTextWrap": false,
          "editorMode": "builder",
          "expr": "zurich_pools_current_fill{pool_name=~\"$pool\"}",
          "fullMetaSearch": false,
          "includeNullMetadata": true,
          "legendFormat": "{{pool_name}}",
          "range": true,
          "refId": "A",
          "useBackend": false
        },
        {
          "datasource": {
            "type": "prometheus",
            "uid": "PBFA97CFB590B2093"
          },
          "disableTextWrap": false,
          "editorMode": "builder",
          "exemplar": false,
          "expr": "max_over_time(zurich_pools_current_fill{pool_name=~\"$pool\"}[90d])",
          "fullMetaSearch": false,
          "includeNullMetadata": true,
          "instant": false,
          "legendFormat": "{{pool_name}}",
          "range": true,
          "refId": "B",
          "useBackend": false
        },
        {
          "datasource": {
            "type": "__expr__",
            "uid": "-100"
          },
          "expression": "$A / $B",
          "refId": "C",
          "type": "math"
        }
      ],
      "title": "Occupancy",
      "transformations": [
        {
          "id": "filterFieldsByName",
          "options": {
            "include": {
              "names": [
                "C"
              ]
            }
          }
        }
      ],
      "type": "gauge"
    },
    {
      "datasource": {
        "type": "prometheus",
        "uid": "PBFA97CFB590B2093"
      },
      "fieldConfig": {
        "defaults": {
          "color": {
            "mode": "thresholds"
          },
          "mappings": [],
          "thresholds": {
            "mode": "absolute",
            "steps": [
              {
                "color": "green"
              },
              {
                "color": "#EAB839",
                "value": 150
              },
              {
                "color": "orange",
                "value": 300
              },
              {
                "color": "red",
                "value": 450
              }
            ]
          }
        },
        "overrides": []
      },
      "gridPos": {
        "h": 6,
        "w": 24,
        "x": 0,
        "y": 6
      },
      "id": 9,
      "options": {
        "displayMode": "gradient",
        "legend": {
          "calcs": [],
          "displayMode": "list",
          "placement": "bottom",
          "showLegend": false
        },
        "maxVizHeight": 300,
        "minVizHeight": 16,
        "minVizWidth": 8,
        "namePlacement": "auto",
        "orientation": "auto",
        "reduceOptions": {
          "calcs": [
            "lastNotNull"
          ],
          "fields": "",
          "values": false
        },
        "showUnfilled": true,
        "sizing": "auto",
        "valueMode": "color"
      },
      "pluginVersion": "12.0.0",
      "targets": [
        {
          "disableTextWrap": false,
          "editorMode": "builder",
          "expr": "zurich_pools_current_fill{pool_name=~\"$pool\"}",
          "fullMetaSearch": false,
          "includeNullMetadata": true,
          "legendFormat": "{{pool_name}}",
          "range": true,
          "refId": "A",
          "useBackend": false
        }
      ],
      "title": "Current Visitor Count",
      "type": "bargauge"
    },
    {
      "datasource": {
        "type": "prometheus",
        "uid": "PBFA97CFB590B2093"
      },
      "fieldConfig": {
        "defaults": {
          "color": {
            "mode": "continuous-BlYlRd"
          },
          "mappings": [],
          "max": 32,
          "min": 10,
          "thresholds": {
            "mode": "absolute",
            "steps": [
              {
                "color": "green"
              },
              {
                "color": "red",
                "value": 80
              }
            ]
          },
          "unit": "celsius"
        },
        "overrides": []
      },
      "gridPos": {
        "h": 6,
        "w": 24,
        "x": 0,
        "y": 12
      },
      "id": 12,
      "options": {
        "displayMode": "gradient",
        "legend": {
          "calcs": [],
          "displayMode": "list",
          "placement": "bottom",
          "showLegend": false
        },
        "maxVizHeight": 300,
        "minVizHeight": 16,
        "minVizWidth": 8,
        "namePlacement": "auto",
        "orientation": "auto",
        "reduceOptions": {
          "calcs": [
            "lastNotNull"
          ],
          "fields": "",
          "values": false
        },
        "showUnfilled": true,
        "sizing": "auto",
        "valueMode": "color"
      },
      "pluginVersion": "12.0.0",
      "targets": [
        {
          "disableTextWrap": false,
          "editorMode": "builder",
          "expr": "zurich_pools_water_temperature{pool_name=~\"$pool\"}",
          "fullMetaSearch": false,
          "includeNullMetadata": true,
          "legendFormat": "{{pool_name}}",
          "range": true,
          "refId": "A",
          "useBackend": false
        }
      ],
      "title": "Water Temperature",
      "type": "bargauge"
    },
    {
      "datasource": {
        "type": "prometheus",
        "uid": "PBFA97CFB590B2093"
      },
      "fieldConfig": {
        "defaults": {
          "color": {
            "mode": "thresholds"
          },
          "fieldMinMax": true,
          "mappings": [],
          "thresholds": {
            "mode": "absolute",
            "steps": [
              {
                "color": "green"
              },
              {
                "color": "text",
                "value": 0
              },
              {
                "color": "red",
                "value": 1
              }
            ]
          }
        },
        "overrides": []
      },
      "gridPos": {
        "h": 5,
        "w": 24,
        "x": 0,
        "y": 18
      },
      "id": 3,
      "options": {
        "colorMode": "value",
        "graphMode": "area",
        "justifyMode": "auto",
        "orientation": "auto",
        "percentChangeColorMode": "same_as_value",
        "reduceOptions": {
          "calcs": [
            "diff"
          ],
          "fields": "",
          "values": false
        },
        "showPercentChange": true,
        "textMode": "auto",
        "wideLayout": true
      },
      "pluginVersion": "12.0.0",
      "targets": [
        {
          "disableTextWrap": false,
          "editorMode": "builder",
          "expr": "zurich_pools_current_fill{pool_name=~\"$pool\"}",
          "fullMetaSearch": false,
          "includeNullMetadata": true,
          "legendFormat": "{{pool_name}}",
          "range": true,
          "refId": "A",
          "useBackend": false
        }
      ],
      "timeFrom": "30m",
      "title": "Fill Difference",
      "type": "stat"
    },
    {
      "datasource": {
        "type": "prometheus",
        "uid": "PBFA97CFB590B2093"
      },
      "fieldConfig": {
        "defaults": {
          "color": {
            "mode": "palette-classic"
          },
          "custom": {
            "axisBorderShow": false,
            "axisCenteredZero": false,
            "axisColorMode": "text",
            "axisLabel": "",
            "axisPlacement": "auto",
            "barAlignment": 0,
            "barWidthFactor": 0.6,
            "drawStyle": "line",
            "fillOpacity": 0,
            "gradientMode": "none",
            "hideFrom": {
              "legend": false,
              "tooltip": false,
              "viz": false
            },
            "insertNulls": false,
            "lineInterpolation": "linear",
            "lineWidth": 1,
            "pointSize": 5,
            "scaleDistribution": {
              "type": "linear"
            },
            "showPoints": "auto",
            "spanNulls": false,
            "stacking": {
              "group": "A",
              "mode": "none"
            },
            "thresholdsStyle": {
              "mode": "off"
            }
          },
          "mappings": [],
          "min": 0,
          "thresholds": {
            "mode": "absolute",
            "steps": [
              {
                "color": "green"
              },
              {
                "color": "red",
                "value": 80
              }
            ]
          }
        },
        "overrides": []
      },
      "gridPos": {
        "h": 11,
        "w": 24,
        "x": 0,
        "y": 23
      },
      "id": 1,
      "options": {
        "legend": {
          "calcs": [],
          "displayMode": "list",
          "placement": "bottom",
          "showLegend": true
        },
        "tooltip": {
          "hideZeros": false,
          "mode": "single",
          "sort": "none"
        }
      },
      "pluginVersion": "12.0.0",
      "targets": [
        {
          "datasource": {
            "type": "prometheus",
            "uid": "PBFA97CFB590B2093"
          },
          "disableTextWrap": false,
          "editorMode": "builder",
          "expr": "zurich_pools_current_fill{pool_name=~\"$pool\"}",
          "fullMetaSearch": false,
          "includeNullMetadata": true,
          "legendFormat": "{{pool_name}}",
          "range": true,
          "refId": "A",
          "useBackend": false
        }
      ],
      "title": "Current Fill",
      "type": "timeseries"
    },
    {
      "datasource": {
        "type": "prometheus",
        "uid": "PBFA97CFB590B2093"
      },
      "fieldConfig": {
        "defaults": {
          "custom": {
            "hideFrom": {
              "legend": false,
              "tooltip": false,
              "viz": false
            },
            "scaleDistribution": {
              "type": "linear"
            }
          }
        },
        "overrides": []
      },
      "gridPos": {
        "h": 10,
        "w": 24,
        "x": 0,
        "y": 34
      },
      "id": 11,
      "options": {
        "calculate": false,
        "calculation": {
          "xBuckets": {
            "mode": "size",
            "value": "10"
          },
          "yBuckets": {
            "mode": "size",
            "value": "10"
          }
        },
        "cellGap": 1,
        "cellValues": {
          "unit": "percentunit"
        },
        "color": {
          "exponent": 0.5,
          "fill": "dark-orange",
          "mode": "scheme",
          "reverse": false,
          "scale": "exponential",
          "scheme": "RdYlGn",
          "steps": 64
        },
        "exemplars": {
          "color": "rgba(255,0,255,0.7)"
        },
        "filterValues": {
          "le": 1e-9
        },
        "legend": {
          "show": true
        },
        "rowsFrame": {
          "layout": "auto"
        },
        "showValue": "auto",
        "tooltip": {
          "mode": "single",
          "show": true,
          "showColorScale": false,
          "yHistogram": false
        },
        "yAxis": {
          "axisPlacement": "left",
          "reverse": true
        }
      },
      "pluginVersion": "12.0.0",
      "targets": [
        {
          "disableTextWrap": false,
          "editorMode": "code",
          "expr": "zurich_pools_current_fill{pool_name=~\"$pool\"} / ignoring(instance,job) max_over_time(zurich_pools_current_fill{pool_name=~\"$pool\"}[90d])",
          "fullMetaSearch": false,
          "includeNullMetadata": true,
          "legendFormat": "{{pool_name}}",
          "range": true,
          "refId": "C",
          "useBackend": false
        }
      ],
      "title": "Current Fill Ratio Heatmap",
      "type": "heatmap"
    },
    {
      "datasource": {
        "type": "prometheus",
        "uid": "PBFA97CFB590B2093"
      },
      "fieldConfig": {
        "defaults": {
          "color": {
            "mode": "palette-classic"
          },
          "custom": {
            "axisBorderShow": false,
            "axisCenteredZero": false,
            "axisColorMode": "text",
            "axisLabel": "",
            "axisPlacement": "auto",
            "barAlignment": 0,
            "barWidthFactor": 0.6,
            "drawStyle": "line",
            "fillOpacity": 0,
            "gradientMode": "none",
            "hideFrom": {
              "legend": false,
              "tooltip": false,
              "viz": false
            },
            "insertNulls": false,
            "lineInterpolation": "linear",
            "lineWidth": 1,
            "pointSize": 5,
            "scaleDistribution": {
              "type": "linear"
            },
            "showPoints": "auto",
            "spanNulls": false,
            "stacking": {
              "group": "A",
              "mode": "none"
            },
            "thresholdsStyle": {
              "mode": "off"
            }
          },
          "mappings": [],
          "thresholds": {
            "mode": "absolute",
            "steps": [
              {
                "color": "green"
              },
              {
                "color": "red",
                "value": 80
              }
            ]
          }
        },
        "overrides": []
      },
      "gridPos": {
        "h": 11,
        "w": 24,
        "x": 0,
        "y": 44
      },
      "id": 13,
      "options": {
        "legend": {
          "calcs": [],
          "displayMode": "list",
          "placement": "bottom",
          "showLegend": true
        },
        "tooltip": {
          "hideZeros": false,
          "mode": "single",
          "sort": "none"
        }
      },
      "pluginVersion": "12.0.0",
      "targets": [
        {
          "disableTextWrap": false,
          "editorMode": "builder",
          "expr": "zurich_pools_water_temperature{pool_name=~\"$pool\"}",
          "fullMetaSearch": false,
          "includeNullMetadata": true,
          "legendFormat": "{{pool_name}}",
          "range": true,
          "refId": "A",
          "useBackend": false
        }
      ],
      "title": "Water Temperature",
      "type": "timeseries"
    },
    {
      "datasource": {
        "type": "prometheus",
        "uid": "PBFA97CFB590B2093"
      },
      "fieldConfig": {
        "defaults": {
          "color": {
            "mode": "palette-classic"
          },
          "custom": {
            "axisBorderShow": false,
            "axisCenteredZero": false,
            "axisColorMode": "text",
            "axisLabel": "",
            "axisPlacement": "auto",
            "barAlignment": 0,
            "barWidthFactor": 0.6,
            "drawStyle": "line",
            "fillOpacity": 0,
            "gradientMode": "none",
            "hideFrom": {
              "legend": false,
              "tooltip": false,
              "viz": false
            },
            "insertNulls": false,
            "lineInterpolation": "linear",
            "lineWidth": 1,
            "pointSize": 5,
            "scaleDistribution": {
              "type": "linear"
            },
            "showPoints": "auto",
            "spanNulls": false,
            "stacking": {
              "group": "A",
              "mode": "none"
            },
            "thresholdsStyle": {
              "mode": "off"
            }
          },
          "mappings": [],
          "thresholds": {
            "mode": "absolute",
            "steps": [
              {
                "color": "green"
              },
              {
                "color": "red",
                "value": 80
              }
            ]
          }
        },
        "overrides": []
      },
      "gridPos": {
        "h": 11,
        "w": 24,
        "x": 0,
        "y": 55
      },
      "id": 14,
      "options": {
        "legend": {
          "calcs": [],
          "displayMode": "list",
          "placement": "bottom",
          "showLegend": true
        },
        "tooltip": {
          "hideZeros": false,
          "mode": "single",
          "sort": "none"
        }
      },
      "pluginVersion": "12.0.0",
      "targets": [
        {
          "disableTextWrap": false,
          "editorMode": "builder",
          "expr": "zurich_pools_max_space{pool_name=~\"$pool\"}",
          "fullMetaSearch": false,
          "includeNullMetadata": true,
          "legendFormat": "{{pool_name}}",
          "range": true,
          "refId": "A",
          "useBackend": false
        }
      ],
      "title": "Reported Max Capacity",
      "type": "timeseries"
    }
  ],
  "preload": false,
  "refresh": "1m",
  "schemaVersion": 41,
  "tags": [],
  "templating": {
    "list": [
      {
        "current": {
          "text": [
            "Freibad Seebach",
            "Hallenbad Oerlikon",
            "Hallenbad City",
            "Freibad Allenmoos",
            "Waermebad Kaeferberg",
            "Freibad Auhof",
            "Frauenbad Stadthausquai"
          ],
          "value": [
            "Freibad Seebach",
            "Hallenbad Oerlikon",
            "Hallenbad City",
            "Freibad Allenmoos",
            "Waermebad Kaeferberg",
            "Freibad Auhof",
            "Frauenbad Stadthausquai"
          ]
        },
        "definition": "label_values(pool_name)",
        "includeAll": true,
        "label": "Pool Name",
        "multi": true,
        "name": "pool",
        "options": [],
        "query": {
          "qryType": 1,
          "query": "label_values(pool_name)",
          "refId": "PrometheusVariableQueryEditor-VariableQuery"
        },
        "refresh": 1,
        "regex": "",
        "type": "query"
      }
    ]
  },
  "time": {
    "from": "now-2d",
    "to": "now"
  },
  "timepicker": {},
  "timezone": "browser",
  "title": "Badis",
  "uid": "5559cefe-330f-4fcb-9819-33952b637b9f",
  "version": 53
}
